database_setup/database_setup.py
database_setup-0.1.2.dist-info/METADATA
database_setup-0.1.2.dist-info/WHEEL
database_setup-0.1.2.dist-info/top_level.txt
database_setup-0.1.2.dist-info/RECORD
